MANIFEST.in
README.md
build.py
requirements-dev.txt
requirements.txt
setup.py
multithreading/__init__.py
multithreading/process.py
pymultithreading.egg-info/PKG-INFO
pymultithreading.egg-info/SOURCES.txt
pymultithreading.egg-info/dependency_links.txt
pymultithreading.egg-info/requires.txt
pymultithreading.egg-info/top_level.txt